foxplainer/__init__.py
foxplainer/data.py
foxplainer/dataset/.DS_Store
foxplainer/dataset/openstack.csv
foxplainer/dataset/openstack_X_test.csv
foxplainer/dataset/qt.csv
foxplainer/dataset/qt_X_test.csv
foxplainer/explainer.py
foxplainer/global_model/.DS_Store
foxplainer/global_model/openstack_LR_global_model.pkl
foxplainer/global_model/openstack_RF_30estimators_global_model.pkl
foxplainer/global_model/qt_LR_global_model.pkl
foxplainer/global_model/qt_RF_30estimators_global_model.pkl
foxplainer/html_string.py
foxplainer/lrxp.py
foxplainer/options.py
foxplainer/pysat/__init__.py
foxplainer/pysat/_fileio.py
foxplainer/pysat/_utils.py
foxplainer/pysat/card.py
foxplainer/pysat/examples/__init__.py
foxplainer/pysat/examples/fm.py
foxplainer/pysat/examples/genhard.py
foxplainer/pysat/examples/hitman.py
foxplainer/pysat/examples/lbx.py
foxplainer/pysat/examples/lsu.py
foxplainer/pysat/examples/mcsls.py
foxplainer/pysat/examples/models.py
foxplainer/pysat/examples/musx.py
foxplainer/pysat/examples/optux.py
foxplainer/pysat/examples/rc2.py
foxplainer/pysat/examples/usage.py
foxplainer/pysat/formula.py
foxplainer/pysat/pb.py
foxplainer/pysat/solvers.py
foxplainer/rndmforest.py
foxplainer/temp.png
foxplainer/tree.py
foxplainer-0.2.0.dist-info/LICENSE
foxplainer-0.2.0.dist-info/WHEEL
foxplainer-0.2.0.dist-info/METADATA
foxplainer-0.2.0.dist-info/RECORD
